MANIFEST.in
README.md
setup.py
Envoy_Cloud.egg-info/PKG-INFO
Envoy_Cloud.egg-info/SOURCES.txt
Envoy_Cloud.egg-info/dependency_links.txt
Envoy_Cloud.egg-info/top_level.txt
src/envoy_cloud/__init__.py
src/envoy_cloud/py.typed
src/envoy_cloud/server.py
src/envoy_cloud/flask/static/apple-touch-icon.png
src/envoy_cloud/flask/static/favicon-16x16.png
src/envoy_cloud/flask/static/favicon-32x32.png
src/envoy_cloud/flask/static/manifest.json
src/envoy_cloud/flask/static/service-worker.js
src/envoy_cloud/flask/static/_next/static/chunks/012ff928-bcfa62e3ac82441c.js
src/envoy_cloud/flask/static/_next/static/chunks/1f110208-cda4026aba1898fb.js
src/envoy_cloud/flask/static/_next/static/chunks/259-c6320349d8f3ff4a.js
src/envoy_cloud/flask/static/_next/static/chunks/58-87db5ef127e7d0b9.js
src/envoy_cloud/flask/static/_next/static/chunks/686-7a99a2d97a992914.js
src/envoy_cloud/flask/static/_next/static/chunks/68a27ff6-a453fd719d5bf767.js
src/envoy_cloud/flask/static/_next/static/chunks/734-99309a157861fd84.js
src/envoy_cloud/flask/static/_next/static/chunks/bd26816a-981e1ddc27b37cc6.js
src/envoy_cloud/flask/static/_next/static/chunks/framework-e23f030857e925d4.js
src/envoy_cloud/flask/static/_next/static/chunks/main-2f10fecca4c74462.js
src/envoy_cloud/flask/static/_next/static/chunks/polyfills-c67a75d1b6f99dc8.js
src/envoy_cloud/flask/static/_next/static/chunks/webpack-c08a82b5c21eeb39.js
src/envoy_cloud/flask/static/_next/static/chunks/pages/app-878ac43f93e00b3f.js
src/envoy_cloud/flask/static/_next/static/chunks/pages/bypass-338530f42d5b2105.js
src/envoy_cloud/flask/static/_next/static/chunks/pages/error-433a1bbdb23dd341.js
src/envoy_cloud/flask/static/_next/static/chunks/pages/index-1401d2c2b63d99cf.js
src/envoy_cloud/flask/static/_next/static/chunks/pages/status-6557d60655b68492.js
src/envoy_cloud/flask/static/_next/static/chunks/pages/account/cancel-63cd9f049103272b.js
src/envoy_cloud/flask/static/_next/static/chunks/pages/account/manage-6ac6d4f0510ced68.js
src/envoy_cloud/flask/static/_next/static/chunks/pages/account/upgrade-d6b322741680e2b4.js
