Metadata-Version: 2.1
Name: Envoy-Cloud
Version: 0.1.5
Summary: A package for Envoy-ChatGPT
Home-page: https://github.com/Einic/envoy-cloud
Author: Einic Yeo
Author-email: Einic@gmail.com
License: UNKNOWN
Project-URL: Source, https://github.com/Einic/envoy-cloud
Project-URL: Tracker, https://github.com/Einic/envoy-cloud/issues
Keywords: OpenAI ChatGPT ChatGPT-Plus
Platform: UNKNOWN
Classifier: Development Status :: 4 - Beta
Classifier: Environment :: Web Environment
Classifier: Framework :: Flask
Classifier: Intended Audience :: Developers
Classifier: Intended Audience :: End Users/Desktop
Classifier: License :: OSI Approved :: GNU General Public License v2 (GPLv2)
Classifier: Natural Language :: English
Classifier: Natural Language :: Chinese (Simplified)
Classifier: Operating System :: MacOS
Classifier: Operating System :: Microsoft :: Windows
Classifier: Operating System :: POSIX :: Linux
Classifier: Programming Language :: JavaScript
Classifier: Programming Language :: Python :: 3.7
Classifier: Programming Language :: Python :: 3.8
Classifier: Programming Language :: Python :: 3.9
Classifier: Programming Language :: Python :: 3.10
Classifier: Programming Language :: Python :: 3.11
Classifier: Topic :: Communications :: Chat
Classifier: Topic :: Internet :: WWW/HTTP
Requires-Python: >=3.7
